{"ocr_results":[{"text":"为刘少奇是对的，邓小平是对的。我还是认为是毛主席对了，我们错了，是我们跟","box":[[29,71],[995,2],[998,55],[33,125]]},{"text":"不上形势。我不可能有先见之明认为毛主席错了。我是心悦诚服地向毛主席请罪。","box":[[31,114],[982,44],[985,91],[34,162]]},{"text":"他们斗我，做了个高帽子，用这么粗的楠竹筒筒，下面划开，用铁丝做个头形圈圈，","box":[[31,151],[992,84],[995,132],[34,200]]},{"text":"上面用弹簧吊一个赤卫军袖章，我挨斗的时候，那高帽子顶上的赤卫军袖章就在弹","box":[[30,189],[996,125],[999,176],[33,239]]},{"text":"簧下晃动晃动晃动晃动·陪斗的时候，就是陪韩林海，我们学校那个极左路线执","box":[[30,229],[994,169],[997,217],[33,277]]},{"text":"行人，他也斗了。陪斗过后，他说：刘国章，你各人找的，请什么罪嘛。我说我是","box":[[31,269],[996,210],[999,257],[34,316]]},{"text":"心悦诚服，我们错了，我们看不清形势。","box":[[38,323],[482,296],[484,320],[40,347]]},{"text":"在斗我的当天晚上，我们学校那个八一五的头头蒋文中，他只讲文斗不讲武斗，","box":[[78,349],[993,296],[995,336],[80,389]]},{"text":"他就找我谈心。他说你对这个运动怎么看？进行到哪一步了？我当时哪里说得清楚","box":[[33,390],[997,339],[999,380],[35,430]]},{"text":"嘛，我只能说这个事情没有了，没有完。可能更大的动荡还在后头。","box":[[34,439],[808,394],[810,424],[36,469]]},{"text":"好，那个时候我在学校就个个都是白眼了。哪个组织都不要我参加。我天天在学","box":[[79,471],[997,426],[999,460],[81,505]]},{"text":"校住校噻，就天天和那些老师在一起，吹龙门阵哪，散步哪，在南泉包到起转哪，","box":[[35,515],[982,469],[984,500],[37,546]]},{"text":"就是过那种逍遥派生活。","box":[[38,558],[301,548],[302,571],[38,581]]},{"text":"没得好久，从安徽开始，造反派就发生分裂了。我肯定不会去参加造反派，因为","box":[[81,592],[996,554],[998,584],[83,622]]},{"text":"我对造反派的很多做法有看法。我们学校有个老红军的儿子王安安，八一五头头是","box":[[35,632],[997,597],[999,628],[36,662]]},{"text":"蒋文中，王安安就编了首歌：石头开花马长角，要我参加八一五，蒋文中变成老太","box":[[36,674],[997,641],[997,668],[37,701]]},{"text":"婆。若干年过后，王安安他爸爸是红四方面军的噻，在三二四医院住院，刚好我妇","box":[[36,713],[997,683],[997,710],[37,740]]},{"text":"夫是一个级别的，他们住在一间病房。他爸爸说我当时日子也不好过，我是红四方","box":[[37,754],[996,727],[996,751],[37,779]]},{"text":"面军的，过草地来回过了三次，解放后也没得好多好日子过。这是那次跟我讲过后","box":[[37,794],[997,770],[997,794],[37,818]]},{"text":"不久他就去世了。现在王安安已经退了，是四川省测绘局的党委书记退的。","box":[[37,832],[895,814],[896,838],[37,856]]},{"text":"到文革过后了，蒋文中因为他文革中的问题受到过处理，若干年后，我觉得还是","box":[[83,871],[999,855],[999,879],[83,895]]},{"text":"应该请他吃顿饭，他毕竟那个时候没有打我，他是那个观点我不能强求。他还在给","box":[[36,910],[999,896],[999,923],[36,937]]},{"text":"我讲，他说我们还可以再搞一次文化大革命。我说你怎么思想还没有转变过来哟。","box":[[36,951],[986,941],[986,965],[36,975]]},{"text":"他说毛主席的孙还在噻，毛新宇还在噻。我后来把这个事情给我们校长讲了，给向","box":[[35,989],[1001,982],[1001,1009],[35,1016]]},{"text":"书记向昌华讲了。向昌华说这崽儿脑壳进水了。","box":[[36,1030],[564,1028],[564,1052],[36,1054]]},{"text":"后来两派分裂了。反到底当时叫砸派，砸派由三种人组成，一种是从八一五里分","box":[[79,1067],[1004,1066],[1004,1096],[79,1097]]},{"text":"裂出来的老造反派，一种是原来军工企业国有企业的工人纠察队，还有就是我们毛","box":[[32,1107],[1005,1109],[1005,1139],[32,1137]]},{"text":"泽东思想红卫兵和赤卫军，遭八一五整过的人，基本上都参加到砸派里面，砸派的","box":[[31,1147],[1005,1151],[1005,1183],[31,1178]]},{"text":"队伍就增大了。","box":[[33,1192],[198,1189],[199,1213],[33,1216]]},{"text":"当时我们学校反到底的中学生红卫兵头头叫邓先明，他爸爸是民盟的，他妈妈是","box":[[77,1226],[1008,1238],[1008,1273],[77,1262]]},{"text":"二十九中的校长，北师大毕业的。他后来当了知青回来在重钢四厂，后来是重钢党","box":[[29,1267],[1011,1281],[1011,1318],[29,1304]]},{"text":"委宣传部副部长退休下来，现在在深圳带孙。我就去找邓先明，因为我恨八一五噻，","box":[[27,1307],[1008,1323],[1008,1363],[27,1347]]},{"text":"我说我来参加你们中学生红卫兵。他说要不得要不得！你是最著名的赤卫军头头，","box":[[27,1349],[996,1370],[996,1406],[27,1385]]},{"text":"你来参加我们红卫兵，好大的影响哦，好大的抹黑哟！他不要我参加，拒绝我参加。","box":[[28,1389],[1010,1411],[1009,1453],[27,1430]]},{"text":"后头我就又当逍遥派嘛。但是我的观点完全是反到底的。","box":[[31,1432],[677,1455],[676,1482],[30,1459]]},{"text":"后头反到底和八一五越来越不对头了。当时我们家住在冶金村，长江剧场那边。","box":[[71,1471],[1014,1497],[1012,1541],[70,1515]]},{"text":"我姐姐在大坪渝办，我妈就长期住在渝办。我就经常往返于大坪和杨家坪的家，那","box":[[23,1510],[1019,1539],[1017,1586],[22,1557]]},{"text":"100","box":[[488,1653],[522,1653],[522,1678],[488,1678]]}],"dimensions":{"height":1701,"width":1086}}