{"ocr_results":[{"text":"如我和蓝亦农他们的合影照片等和有关文革的资料，以及我的文学历史书籍，当时","box":[[137,70],[1176,41],[1178,109],[138,138]]},{"text":"就有两大箩筐，但后来文革结束，我被抓，他们抄走了，最让我痛心的是资料和书","box":[[138,114],[1177,85],[1179,148],[139,177]]},{"text":"的散失，书只还了我儿本，其中有一本《资治通鉴》，但《石头记》和另外的《资治","box":[[140,156],[1175,128],[1177,189],[141,217]]},{"text":"通鉴》几十本却没有还我，还有我的家具也被抄走没还我，只是赔了点钱给我。","box":[[143,208],[1129,174],[1130,221],[144,255]]},{"text":"还有就是文革期间，为保住我们几十号的命，加上粮油供应短缺，连起码的小菜","box":[[191,238],[1176,216],[1177,272],[193,294]]},{"text":"都买不到，一日三餐也够我们几个头头儿操心的，有时出外还要担心被对方的埋伏","box":[[143,280],[1174,259],[1175,313],[144,334]]},{"text":"暗杀，我住在厂里单身宿舍，老工人还来为我站班，怕出现王庭学那样的情况，仅","box":[[144,324],[1173,303],[1174,353],[145,374]]},{"text":"就这些来说，文革确是一部让人伤心的历史。","box":[[152,378],[691,369],[692,399],[152,408]]},{"text":"问：王庭学被抓是怎么回事？","box":[[205,458],[546,455],[547,482],[205,485]]},{"text":"他被抓走时在厂里单身宿舍睡觉，我们厂里有个技术员（他是反到底派的)，他","box":[[202,533],[1167,520],[1168,557],[202,570]]},{"text":"暗通了航锋战斗团的人来，深夜两点多钟把他从睡梦中绑架到了航锋那里去了。他","box":[[153,574],[1165,563],[1166,597],[153,608]]},{"text":"后来指给我看，腰部左侧被戳了一刀。","box":[[158,619],[607,619],[607,642],[158,642]]},{"text":"问：当时你们都没有人晓得呀？","box":[[209,697],[574,698],[574,722],[209,721]]},{"text":"我们没有这样的心理准备，不知道会发生如此严重的事情。只是第二天发现人不","box":[[209,777],[1159,775],[1160,799],[209,801]]},{"text":"见了，我们四处寻找，后来才听说被航锋劫持了，被关了半年多才放回来。厂里因","box":[[159,814],[1160,815],[1160,842],[159,841]]},{"text":"为他的这段经历而选他为革委会副主任，现在他住在美国她女儿家里，每年他都回","box":[[159,854],[1159,855],[1159,882],[159,881]]},{"text":"来一次，在美国他给我打过电话，又有半年多了不知他的身体情况怎样了，他年龄","box":[[158,891],[1159,894],[1158,924],[158,921]]},{"text":"比我小，现在他还没满七十，可能67岁左右。他老丈人在西师附中教书，还听说朱","box":[[160,930],[1160,934],[1159,964],[160,960]]},{"text":"德的一个儿子于革命战争艰苦年代在他老丈人家里寄养过，文革中朱德逝世后还给","box":[[159,969],[1158,976],[1157,1006],[159,999]]},{"text":"他老丈人发了吊函，他也去参加过朱德的追悼会，把来往的信件交给了治丧委员","box":[[158,1006],[1160,1014],[1159,1048],[158,1040]]},{"text":"会，至于那些信函可能保存在博物馆。那时，我还经常帮他修在荷花池的北碚二","box":[[159,1044],[1159,1055],[1158,1089],[159,1078]]},{"text":"层楼老屋，现在听说被征收重新修房了。","box":[[162,1086],[638,1090],[638,1117],[162,1113]]},{"text":"问：听说金光中在他家里开会被清查了？","box":[[213,1163],[686,1169],[685,1196],[213,1190]]},{"text":"他是被清查过一段时间的，市里派人来调查过。文革后，周家喻、黄廉、熊代富,","box":[[206,1234],[1159,1254],[1158,1297],[205,1277]]},{"text":"那半年每个月都要到我家里来耍。特别是反击右倾翻案风之前，黄廉、周家喻来问","box":[[159,1273],[1162,1294],[1161,1337],[158,1317]]},{"text":"我：黄二你看搞不搞得？我说：看中央的决心来看还是要搞的。","box":[[161,1310],[919,1332],[918,1369],[160,1348]]},{"text":"问：张祖祥后来被清查没有？","box":[[213,1395],[550,1402],[549,1429],[212,1422]]},{"text":"张祖祥被审查了一段时间，但没有被抓，反到底是傅主学、赵湘、文新华都被处","box":[[206,1465],[1163,1488],[1162,1542],[204,1519]]},{"text":"理过的。","box":[[167,1513],[259,1513],[259,1538],[167,1538]]},{"text":"1","box":[[24,1539],[57,1539],[57,1580],[24,1580]]},{"text":"问：你文革初期，从公安局调到厂里来，是工作调动吗？","box":[[215,1581],[883,1614],[881,1647],[213,1614]]},{"text":"182","box":[[641,1724],[676,1724],[676,1749],[641,1749]]}],"dimensions":{"height":1755,"width":1240}}