{"ocr_results":[{"text":"辜的。但现在聚会时，任思成（当年黄的贴身保卫）说：“老黄还不改掉这个老毛孩，","box":[[188,61],[1167,29],[1169,110],[191,141]]},{"text":"今后要死在这个上面！”用手指作了个不雅动作。","box":[[200,131],[758,103],[760,144],[202,172]]},{"text":"问：王英是哪个单位的？","box":[[259,216],[530,207],[531,235],[260,244]]},{"text":"市蔬菜公司的。（插话：黄廉的回忆录里面反复提到王英。）黄对我说起王英的","box":[[247,268],[1168,244],[1170,311],[249,335]]},{"text":"情况，王英在外地小学教书想调回重庆。王参加造反军北上告状时，其丈夫因王英","box":[[192,309],[1170,286],[1172,353],[194,375]]},{"text":"年青漂亮，为免发生情况，要黄廉多关照些。所以王英的活动，黄都会注意到。二","box":[[195,356],[1166,332],[1168,389],[197,413]]},{"text":"月镇反后，王解决了艰难的调动问题，到市蔬菜公司上班，黄认定是市委鲁大东书","box":[[198,398],[1168,376],[1169,430],[200,453]]},{"text":"记解决的。王英后来没出来活动了，加上鲁书记掌握了黄的一些情况，所以黄肯定","box":[[198,437],[1168,416],[1169,473],[200,494]]},{"text":"王英是出卖了他，来作调回重庆的交易。","box":[[207,497],[669,486],[670,516],[208,527]]},{"text":"王英在煤二所时搞接待，我有事找她，看见杨国成笑嘻嘻向王耳语，王一脸严","box":[[258,526],[1165,505],[1166,550],[259,571]]},{"text":"肃把杨推开，加上其他的事情，我才写了那张“记取李闯王进京失败的历史教训”","box":[[205,570],[1158,549],[1159,590],[206,611]]},{"text":"的大字报。北上回来后就很少见过王的面。去年听说她去过沙区公园 815 烈士墓公","box":[[206,608],[1165,592],[1166,633],[207,649]]},{"text":"园管理办公室，向收集文革资料的记者谈文革经历，我认为是对历史敢于负责的表","box":[[207,650],[1165,636],[1166,674],[208,688]]},{"text":"现。：","box":[[210,696],[309,700],[308,727],[208,723]]},{"text":"问：在人民小学那里的联络站，你去过没有？","box":[[268,777],[775,770],[775,797],[269,804]]},{"text":"没去过。（插话：实际上联络站是造反军司令部的李方成在负责，李方成说黄","box":[[267,856],[1162,850],[1163,876],[267,883]]},{"text":"廉基本没到那里去。）","box":[[218,898],[451,898],[451,919],[218,919]]},{"text":"用大字报传单造舆论，说市委黑手伸进造反派，黄是派进来的。再加上同渣","box":[[269,937],[1162,934],[1163,958],[269,961]]},{"text":"洞放出来的“叛徒”罗广斌勾结，这一派肯定就被抹黑了噻！当时揭发“重庆造反","box":[[216,977],[1163,975],[1164,999],[216,1001]]},{"text":"派联络站”实为“廉罗站”，就是要把二人捆在一起。联络站的李方成是个怎样的人、","box":[[217,1016],[1164,1016],[1164,1043],[217,1043]]},{"text":"怎样活动的？我真的没得更多的了解。","box":[[219,1057],[645,1057],[645,1081],[219,1081]]},{"text":"罗广斌被部队242红总关押在马家堡（解放军后工学院）教学大楼，242的小报","box":[[269,1093],[1168,1095],[1168,1128],[269,1126]]},{"text":"出专刊描写抓罗经过及自杀经过，刊登自杀现场和遗物照片，称罗是跳楼畏罪自杀","box":[[214,1131],[1171,1135],[1171,1172],[214,1168]]},{"text":"身亡的。我的学生家住院内，他到过罗的出事现场，罗是仰面朝天躺在地上，头顶","box":[[214,1171],[1173,1176],[1172,1216],[214,1210]]},{"text":"开花、脑浆暴露、眼珠突起在外面，但地上无丝毫血流痕迹。小孩述说亲眼所见，","box":[[213,1209],[1162,1218],[1161,1258],[213,1249]]},{"text":"应当最为真实吧，迹象根本就不像是自杀的！当时重庆闹自杀风，我记得还有重大","box":[[211,1249],[1177,1257],[1176,1302],[211,1295]]},{"text":"校长郑思群、重庆公安局局长孙斌、市中区唐区长。（插话：罗广斌是不是自杀的","box":[[211,1290],[1178,1297],[1177,1344],[211,1337]]},{"text":"事，几次专案组搞调查都肯定是自杀，家属至今不承认是自杀。)","box":[[215,1329],[991,1346],[990,1383],[214,1366]]},{"text":"问：你跟罗接触过没有？","box":[[273,1419],[544,1421],[543,1445],[273,1443]]},{"text":"只有那一次接触。我们谈了一阵之后，又有陈发荣、陈未友到场。大家一直认","box":[[262,1487],[1184,1498],[1183,1562],[261,1550]]},{"text":"为 815 派联合指挥部内部分歧很大，没有可能使意见一致。如重大815和西师八三","box":[[208,1525],[1185,1538],[1184,1605],[207,1592]]},{"text":"196","box":[[682,1665],[716,1665],[716,1690],[682,1690]]}],"dimensions":{"height":1755,"width":1240}}