{"ocr_results":[{"text":"两派都有还是一派为主我们就不清楚了。这次讲了一个多小时。然后院领导就说，","box":[[124,51],[1130,0],[1133,53],[127,104]]},{"text":"既然你们来了，干脆我们晚上再搞一个军民联欢活动。我们接受了这个建议过后，","box":[[125,90],[1129,44],[1131,97],[128,143]]},{"text":"马上打电话给甘廷荣他们，叫财贸九二一的，也就是财贸井冈山的文艺宣传队上山","box":[[126,128],[1144,88],[1146,142],[128,182]]},{"text":"来。他们是后来的，我们先来，下午完了才打电话通知他们来的。他们赶在晚饭前","box":[[125,169],[1144,133],[1146,188],[127,224]]},{"text":"就来了。","box":[[134,227],[230,227],[230,251],[134,251]]},{"text":"因为林园没有围墙，就在一个大操场里演出，贴出海报去一宣传，那个文化大","box":[[180,254],[1145,225],[1146,273],[182,302]]},{"text":"革命期间，能够看节目演出还是很高兴的事情。附近的居民哪农民哪都来了。还有","box":[[127,298],[1144,270],[1145,317],[128,344]]},{"text":"附近的学生也来了。我们几个坐在前排，跟院领导坐在一起。开始演都很正常，都","box":[[129,341],[1145,316],[1146,360],[130,385]]},{"text":"是歌颂毛主席呀，歌颂共产党呀，歌颂文化大革命呀，唱啊跳啊，都没得啥子。大","box":[[130,385],[1144,363],[1145,403],[131,425]]},{"text":"概演了一个把钟头，后来就演了个节目，控诉二月镇反的节目，演到反到底战士被","box":[[130,427],[1143,407],[1144,446],[131,467]]},{"text":"抓起来了，戴着脚手，押起走，悲哀的场面。演到这里，可能学员中有八一五","box":[[130,471],[1141,454],[1142,490],[131,508]]},{"text":"的，就认为不是事实，就开始吼，发嘘声，台上继续演，接着就往台上掷石块、泥","box":[[131,512],[1142,499],[1143,536],[131,549]]},{"text":"巴，前面的往台上掷，后面的往前面掷，没有掷上台的就掷到我们前排来了。包括","box":[[133,555],[1141,546],[1142,579],[133,588]]},{"text":"院领导也遭到了袭击，台上的演员也有的受伤了。有的乐器也被砸坏了。开始学院","box":[[132,597],[1140,592],[1140,622],[132,627]]},{"text":"的警卫连出来维持秩序，但那些人根本不听。这时才意识到不行了，院领导就叫我","box":[[132,637],[1139,636],[1139,667],[132,668]]},{"text":"们赶快走，叫警卫连：一定要把我们请来的客人保护好。连长马上把警卫连战士叫","box":[[132,679],[1139,680],[1139,710],[132,709]]},{"text":"来站了两排，成为一个夹道，叫我们这几个人通过他们的夹道，出大门就是到歌乐","box":[[133,721],[1137,727],[1137,754],[133,748]]},{"text":"山的一条马路，马路对面是他们警卫连的营房，我们就到营房去了。营房去了过后，","box":[[135,762],[1135,770],[1135,797],[135,789]]},{"text":"就叫我们分散，三个两个到他们战士的寝室去。","box":[[136,805],[688,811],[687,835],[136,829]]},{"text":"问：你是跟哪个在一起？","box":[[191,887],[470,892],[470,916],[191,911]]},{"text":"段炳森、刘开科嘛，我们机关的几个熟的在一起。嘱咐我们不要出来，怕出事。","box":[[188,967],[1139,989],[1138,1019],[188,997]]},{"text":"过了一会儿，就听到外面闹起来了，嘈杂声越来越大，喊“抓出来”“揪出来”，又","box":[[134,1006],[1140,1033],[1139,1063],[133,1036]]},{"text":"听到警卫战士喊“不要往前冲”，在阻挡，突然就听见“啪啪啪·…·.”响了一排枪，","box":[[134,1047],[1128,1076],[1127,1107],[133,1078]]},{"text":"枪一响，就鸦雀无声了。我们说是在对空鸣枪了。没过几分钟，又哄闹起来了，高","box":[[131,1086],[1143,1118],[1142,1155],[130,1122]]},{"text":"喊“抓出来哟”，到底是抓开枪的人还是来抓我们，我们也不清楚。听到外面的广播","box":[[130,1125],[1143,1162],[1142,1199],[129,1162]]},{"text":"也在喊：“八一五的战友们，现在警卫连抓人了，请你们赶快来声援！”声音越来越","box":[[131,1166],[1143,1206],[1142,1243],[130,1203]]},{"text":"大了，可能就在门外一点，隔我们几公尺近了。又听到一排枪响，随后警卫连战士","box":[[128,1208],[1143,1249],[1142,1289],[127,1248]]},{"text":"就推门进来，已惊惊慌慌的，说，出事了，赶快跟我们走。往后山走。我们也不晓","box":[[128,1247],[1145,1293],[1143,1336],[126,1290]]},{"text":"得出了什么事，把门开了一出来，就看到坝子里已经倒了一片了。走在路上我们就","box":[[126,1290],[1145,1336],[1143,1380],[124,1334]]},{"text":"问是怎么回事。他们就说边走边讲，说“蛋糕兵”——他们对学院的八一五派这样","box":[[125,1332],[1146,1378],[1144,1425],[123,1378]]},{"text":"称呼——要来抓你们这些头头，我们不能让他们把我们保护的人抓起去了。如果把","box":[[123,1374],[1146,1423],[1144,1469],[121,1421]]},{"text":"你们抓起去了，一个是我们失职，没有完成好任务，一个你们是头头，如果抓起去","box":[[123,1417],[1146,1466],[1144,1513],[121,1464]]},{"text":"了，受了伤害了，那重庆两派不知又要闹成什么样子。那不晓得还要死好多人。所","box":[[122,1460],[1148,1507],[1146,1558],[120,1511]]},{"text":"以他们冲得凶了，我们最先是按九五命令，对空鸣枪示警，他们就误会了，以为我","box":[[121,1500],[1147,1551],[1145,1602],[118,1551]]},{"text":"们不敢开枪。继续冲，我们就往地上开枪，警告他们不要再往前冲，他们前面的人","box":[[119,1544],[1146,1595],[1144,1646],[116,1595]]},{"text":"258","box":[[606,1694],[644,1694],[644,1722],[606,1722]]}],"dimensions":{"height":1755,"width":1240}}