{"ocr_results":[{"text":"人是允许的。那么都自命为左派，我是左派，我打你坏人，有什么不可以呢？左派","box":[[122,128],[1087,140],[1087,194],[121,182]]},{"text":"打右派，毛和中央都是允许的。比如，上海那个康平路事件，毛和中央都是赞成的。","box":[[124,170],[1084,182],[1084,232],[123,220]]},{"text":"上海工总司夺权过后，有个反对派叫上柴联司，它也是觉得没有得到重视，要跟工","box":[[124,210],[1084,222],[1084,271],[123,260]]},{"text":"总司对着干。实际上作些安抚也是可以解决的，但是工总司就不给你安抚，要把你","box":[[124,253],[1084,262],[1084,309],[123,300]]},{"text":"踏平。后来我看过资料，说毛看过那个录像资料很赞同（插话：毛当时就在上海，","box":[[123,293],[1068,304],[1068,350],[122,339]]},{"text":"通过实况看了现场情况）。他很赞赏这种做法，这个就是政策错误。像八一五派就认","box":[[123,334],[1082,343],[1082,390],[122,381]]},{"text":"为他们是左派，他们是部队支持的。我们反到底派认为革联会是中央不承认的，也","box":[[124,375],[1082,383],[1082,430],[124,422]]},{"text":"认为自己是左派。其实我们那个时候，真的是很诚心地要用鲜血和生命保卫毛主席","box":[[125,417],[1079,425],[1079,469],[125,461]]},{"text":"革命路线。我们那个时候很幼稚、很单纯，头脑简单。","box":[[127,459],[740,468],[740,505],[126,495]]},{"text":"我的觉醒就是在九五命令以后，我跟马文光说，这个运动不要参加了，死了都是","box":[[167,501],[1078,507],[1078,546],[167,540]]},{"text":"白死。两派都是革命组织，你从理论上也说不通嘛。老马后来也逐渐退出了，他有","box":[[126,541],[1077,545],[1077,585],[126,581]]},{"text":"支手枪在1967年时没有交，还留下来要了一阵，后来1968年发了七二三布告后才","box":[[126,583],[1074,587],[1074,623],[126,619]]},{"text":"交出去的。好像是毛在北京接见五大领袖，说了谁再有枪，再搞武斗，就是土匪，","box":[[127,624],[1057,629],[1057,662],[127,657]]},{"text":"就要剿灭，这样才把全国武斗平息了。","box":[[129,665],[555,667],[555,697],[129,695]]},{"text":"我在文化大革命的经历就是这样三件大事：一是跟那个公安局预审科长上北京告","box":[[171,706],[1070,707],[1070,738],[171,737]]},{"text":"状，二是七三○海战，三是八一八在学校。九五命令交枪后就离开了。","box":[[131,748],[913,751],[913,774],[131,771]]},{"text":"问：后头分配过后，又理抹这些事没得？","box":[[175,827],[624,829],[624,852],[175,850]]},{"text":"理抹了的，到了单位过后又清理。我基本上是到渡口过后，清理了就没有再清理","box":[[175,907],[1066,907],[1066,930],[175,930]]},{"text":"了，因为我不是头头。我们有的同学当头头的，十二大过后清理三种人，一直受影","box":[[133,946],[1065,945],[1065,969],[133,970]]},{"text":"响。像我们那个同学邹际蛟，一直到上世纪九十年代，在单位上才当上科长，还入","box":[[131,985],[1065,984],[1065,1008],[131,1009]]},{"text":"了党。我后来在单位上也入了党的，后来上面的标准变了。我那阵在单位是搞技术","box":[[130,1023],[1065,1022],[1065,1049],[130,1050]]},{"text":"的，当轮机长，后来搞技术管理。因为工作表现好，就入了党，那时听上面说文化","box":[[129,1061],[1065,1059],[1065,1089],[129,1091]]},{"text":"大革命的事不追究了，要看现实表现。","box":[[129,1102],[549,1101],[549,1128],[129,1129]]},{"text":"我还是认同中央说的文革是内乱，但是中央不主张把这件事一再拿来说，想把这","box":[[170,1138],[1066,1135],[1066,1169],[170,1172]]},{"text":"个事冷下来淡化它。民间的研究一直在深入，想把许多没有搞清的事情搞清楚。我","box":[[127,1176],[1068,1173],[1068,1210],[127,1213]]},{"text":"还是赞成改革开放时期的许多政策，发展是硬道理。我们有些同学聚在一起时，有","box":[[125,1216],[1067,1211],[1067,1248],[125,1252]]},{"text":"人说这个不行，那个政策不对，我还是认为这些年的政策是对的，稳定为上，发展","box":[[125,1252],[1068,1249],[1068,1289],[125,1292]]},{"text":"为上。","box":[[129,1298],[187,1301],[186,1327],[128,1324]]},{"text":"问：那个赵其富，他当时是不是航锋的呢？","box":[[170,1380],[647,1372],[648,1403],[170,1411]]},{"text":"他实际上是团部的幕僚、骨干分子，他是航锋派到红一方面军的代表，在那边有","box":[[165,1448],[1067,1444],[1067,1488],[165,1492]]},{"text":"职务。","box":[[128,1491],[189,1499],[186,1525],[124,1517]]},{"text":"问：他们红一方面军曾经一度驻在河运校里头吗？","box":[[169,1574],[724,1565],[724,1599],[169,1608]]},{"text":"291","box":[[574,1678],[606,1678],[606,1703],[574,1703]]}],"dimensions":{"height":1755,"width":1240}}