{"ocr_results":[{"text":"但是，我没想到厄运降临到了我的头上。回到厂里，我刚洗完澡，接到厂工会","box":[[97,81],[949,39],[951,85],[99,128]]},{"text":"主席的电话，叫我到工会来一趟。我不知道他葫芦里卖的什么药。他对我说：“这也","box":[[44,121],[947,78],[949,123],[46,165]]},{"text":"是对你好，学习提高嘛。”接着又说：“没几个人，就在这里的二楼。”我答道：要得","box":[[43,158],[948,117],[950,161],[45,201]]},{"text":"嘛！我心想，看你们搞什么名堂！我转身要走：“我要回去拿洗漱用具。”他拦住我","box":[[42,195],[948,157],[950,200],[44,239]]},{"text":"说：“让工会的人去给你拿！”话音刚落，保卫科科长和几个民兵进来了，见势不对，","box":[[45,237],[944,198],[946,236],[47,274]]},{"text":"我问他们什么意思，都不说话。这时，工会主席才挑明了本意：这叫隔离学习班。","box":[[46,277],[935,239],[937,272],[48,310]]},{"text":"接下来，我就被几个民兵关进了二楼那间黑屋，里面有铁床一张，独凳一个，旁边","box":[[44,311],[945,278],[947,314],[46,348]]},{"text":"摆着一个消防灭火器，照明的白炽灯升到了屋顶，开关也在够不到的高处，而窗户","box":[[45,352],[944,319],[946,352],[46,385]]},{"text":"是用铁板开了一些空，用作通风，当然是加固了。而且家人送来的被盖，也要打开","box":[[46,388],[944,358],[946,392],[47,422]]},{"text":"了检查，说是不能有硬器带入。我在里面待了一天多时间后，派了两个我熟知的老","box":[[47,429],[945,399],[946,430],[48,460]]},{"text":"头来看护我。从此，我被囚禁在里面，小渡在屋里解，大渡有看护人带着在外面厕","box":[[46,466],[944,440],[945,470],[47,496]]},{"text":"所解决。每天只有半小时的放风时间，对我的定性是政治犯。但我不觉得孤单，除","box":[[48,504],[944,481],[944,509],[49,531]]},{"text":"每天有送来的报纸看，外面的干姐姐还来看望我，我的战友更是给我送来香烟，嘉","box":[[47,542],[944,521],[944,547],[48,568]]},{"text":"陵江、巨浪、大渡河牌子的烟，任由我抽。","box":[[50,581],[492,572],[492,595],[50,604]]},{"text":"问：当时说要清理几个大案，你们厂里清理了吗？","box":[[105,654],[622,645],[623,668],[106,677]]},{"text":"对我来说，大概有五个案。第一个案子，说我把红代会的人关在电机房烤成了","box":[[103,729],[938,720],[938,741],[104,750]]},{"text":"“人干”，扔到凤鸣山的河沟里。","box":[[60,766],[384,764],[384,785],[60,787]]},{"text":"第二个案子，说我文革结束要上山打游击，但我没有承认。这个事的缘起是，","box":[[103,802],[927,797],[927,821],[104,826]]},{"text":"周家喻他们召开了一个有50人参加的长安会议，我也去了。要大家准备第二次斗争，","box":[[49,839],[940,837],[940,861],[49,863]]},{"text":"了解到铜梁的军库有武器，可以武装一个师。为此我亲自去了一趟，和那里的某师","box":[[49,877],[941,875],[941,899],[49,901]]},{"text":"政委摆谈了当时的形势，以及需要武器事宜，后来成都学习班上，成都军区和重庆","box":[[49,916],[942,916],[942,939],[49,939]]},{"text":"警备区的四个人调查我三个星期，但我拒不承认，而翟代表承认后受到了处理。我","box":[[47,951],[943,954],[943,978],[47,975]]},{"text":"说，那时我在知青办公室去，只是看望知青而已。如果要说我在某些场合谈到此事，","box":[[46,987],[940,991],[940,1019],[46,1014]]},{"text":"那是酒后失言，叫我签字我不签。我说，真要我签，我可以签，但要这样签“胡说","box":[[45,1024],[943,1032],[943,1059],[45,1052]]},{"text":"八道也相信？”这对我来说是个很重要的事情。","box":[[46,1063],[544,1066],[544,1091],[46,1088]]},{"text":"还有在天原厂出了一个事。当时天原化工厂有个八一五派的王某被反到底的殴","box":[[99,1099],[945,1108],[945,1139],[98,1129]]},{"text":"打，我们的人过去帮忙。我也去了，把一个叫詹成福的反到底的人打伤了，伤势有","box":[[42,1135],[943,1149],[943,1179],[41,1166]]},{"text":"些严重。","box":[[46,1177],[126,1179],[125,1201],[45,1199]]},{"text":"第三件事说我在中梁山地区，在反击右倾翻案风期间，造成工厂停产。我争辩","box":[[96,1212],[947,1227],[947,1261],[95,1246]]},{"text":"道，这是因为你们党委想抢头彩，在二月初在全厂写出“反击右倾翻案风”的标语","box":[[40,1248],[948,1266],[947,1303],[39,1286]]},{"text":"口号，而且开会要各支部提高认识后，我们的大字报、大标语才跟着贴了出来的。","box":[[43,1288],[934,1308],[934,1342],[42,1321]]},{"text":"这件事也纠缠得比较久。","box":[[43,1328],[295,1336],[295,1359],[42,1351]]},{"text":"第四件事就是所谓的档案问题和枪支问题。特别是枪支问题，一直没有查到枪","box":[[93,1362],[950,1383],[949,1424],[92,1403]]},{"text":"的下落。至于档案问题，是说有几个人的专门档案不见了，问题不小，但又追查到","box":[[37,1398],[952,1422],[951,1465],[36,1441]]},{"text":"了我这里来了，说和我当司令时有连带责任，好在这个管档案的人，是个持反到底","box":[[38,1435],[952,1461],[950,1504],[37,1478]]},{"text":"92","box":[[472,1566],[496,1566],[496,1590],[472,1590]]}],"dimensions":{"height":1615,"width":1071}}