{"ocr_results":[{"text":"第十五学","box":[[446,0],[622,0],[622,31],[446,31]]},{"text":"265","box":[[1597,1],[1673,1],[1673,32],[1597,32]]},{"text":"愈司務長制定了工作报表，哪些是以颌代報，搞得清清楚楚，以後全軍","box":[[0,214],[1641,161],[1645,282],[0,336]]},{"text":"連除司務長就统一了報表。","box":[[15,340],[586,287],[592,349],[21,402]]},{"text":"第二，管部制，","box":[[98,419],[494,382],[499,435],[103,471]]},{"text":"在後勤系統，管不是一級保障機構·管部單位很小，抵有十個人，","box":[[99,474],[1623,438],[1625,528],[102,564]]},{"text":"我記得抵定福一個管理員，一個炊事員。對管的制没有什不同意","box":[[8,559],[1650,511],[1654,621],[12,670]]},{"text":"見，很快就定下來了。","box":[[25,687],[489,641],[494,693],[30,740]]},{"text":"第三，團後勤處福制。","box":[[117,758],[609,723],[613,777],[121,812]]},{"text":"團是一级後勤，是保障機構，對全團負賣保障任務，完成任務，","box":[[110,821],[1639,785],[1641,871],[112,907]]},{"text":"在制上應當「肝鵬俱全」·後勤機關，除增設了一名職勤參課之外，","box":[[16,910],[1644,866],[1647,963],[19,1007]]},{"text":"没有新的增减。團後勤处最大的變動是勤務分除：","box":[[25,1009],[1133,964],[1136,1044],[29,1089]]},{"text":"（1）增供應库·這個庫包括軍需品·弹藥等的保管和分發，還","box":[[110,1083],[1666,1050],[1667,1132],[112,1164]]},{"text":"有勤務班，携任装卸作業和警衛任務。","box":[[33,1189],[928,1146],[932,1216],[36,1259]]},{"text":"（2）增修理所·其主要任務是修理檐械·營具丶炊具等，這是團","box":[[118,1261],[1667,1228],[1668,1306],[119,1339]]},{"text":"的「加工廠」·對後勤業務是很重要的。","box":[[35,1366],[907,1327],[910,1392],[38,1430]]},{"text":"（3）衡生除保持原樣，但逐年分期分批配了救護車。","box":[[122,1445],[1305,1411],[1307,1479],[124,1513]]},{"text":"第四，師後勤部制。","box":[[138,1545],[628,1520],[631,1569],[140,1595]]},{"text":"在野軍裹師後勤部是重要的機構，它常常接受軍區或基地分部的","box":[[132,1618],[1679,1585],[1680,1657],[134,1690]]},{"text":"直接供應，同時，組織全師的運輸·物資供應·傷病員收容轉送丶及裝","box":[[39,1711],[1685,1671],[1687,1747],[41,1786]]},{"text":"維修等全部的後勤保障任務，因此，師後勤部必须有合理的組織機構","box":[[44,1799],[1688,1759],[1690,1835],[46,1876]]},{"text":"才能完成任務。","box":[[52,1909],[363,1889],[366,1938],[55,1958]]},{"text":"師後勤部機關，除增编勤科之外，人員增减不多，師後勤部有：","box":[[141,1979],[1673,1946],[1674,2010],[142,2044]]},{"text":"载勤、财務、軍需、軍械、衛生、營房等各科。","box":[[55,2076],[1111,2045],[1113,2106],[57,2137]]},{"text":"師後勤的勤務分像：","box":[[150,2171],[591,2154],[592,2200],[152,2216]]},{"text":"（1）師衛生管改師圈醫院·這個醫院有：门诊、内科、外科三","box":[[145,2252],[1697,2220],[1698,2276],[147,2308]]},{"text":"调科和防疫所，平时可以完成治療任務，载時可以完成收容後送傷病員","box":[[62,2348],[1698,2311],[1700,2364],[63,2401]]},{"text":"的任務·同時，這種制可以容納技術比较高的醫務人員，軍除倡醫","box":[[64,2439],[1703,2402],[1704,2454],[65,2490]]},{"text":"科大學的星業生分到部队，不但可以充實基唇，也能學有所用，","box":[[67,2531],[1495,2499],[1496,2547],[68,2579]]},{"text":"（2）增福汽車運輸連、畜力運輸連、修理连各一-固·修理连的其主","box":[[155,2619],[1709,2586],[1710,2635],[156,2668]]},{"text":"要任務是任檐械：汽車的修理，除了能修檐械之外，車幅要能達到中","box":[[68,2712],[1712,2674],[1713,2727],[70,2765]]},{"text":"修的水本。在師建立装比较好、技循水平比较高的修理機構，無平","box":[[71,2801],[1717,2768],[1718,2821],[72,2854]]},{"text":"時、峨时都有重要作用·","box":[[69,2893],[606,2888],[606,2936],[69,2941]]}],"dimensions":{"height":2991,"width":1774}}