{"ocr_results":[{"text":"部除的生產，时限制在種和飬雨倡方面，商業是禁區·種和養都","box":[[108,13],[1707,19],[1707,144],[108,138]]},{"text":"是“生财對部除生活有直接的利益，對圆家也是有利的·商業是「分","box":[[9,106],[1718,85],[1719,237],[11,258]]},{"text":"對·道對部除經濟收入有利，但封部除建设是福焉不利的·因篇商亲是","box":[[9,193],[1720,176],[1722,328],[10,345]]},{"text":"最容易毒害幹部和部除的，同時，軍除經管商業對國家是不利的。","box":[[16,289],[1707,270],[1709,410],[17,430]]},{"text":"了部缘生活上的方便，在地商業部門的支持下·部除建立過自己的","box":[[20,380],[1723,364],[1724,502],[22,517]]},{"text":"軍人服務社，道是為了服務·亚不是商業，我是始終反對部除經管商業","box":[[22,473],[1725,457],[1726,589],[23,606]]},{"text":"的，在當時的情况下，我為我的主張和做法是對的。","box":[[31,580],[1301,551],[1303,656],[33,685]]},{"text":"全軍歷次農副業生產會","box":[[532,764],[1231,773],[1230,833],[531,824]]},{"text":"一九六一年十一月一日，我在第一次全軍晨副業生產會上報告了","box":[[134,871],[1722,866],[1722,960],[134,965]]},{"text":"全軍晨副業生產的情况。","box":[[53,1003],[601,967],[604,1022],[57,1058]]},{"text":"像這樣專門的體副業生會；解放以後還是第一次·這次會是根","box":[[140,1062],[1729,1052],[1730,1139],[140,1148]]},{"text":"攘林總對全軍明年任務的安排而開的·軍委和林總下了很大决心，把軍","box":[[45,1158],[1732,1140],[1733,1233],[46,1251]]},{"text":"除搞晨副業生產定一九六二年中心任務之一，了完成這個任務，軍","box":[[47,1252],[1734,1232],[1735,1322],[48,1342]]},{"text":"委對全軍一九六二年的工作，根據不同任務，將部除分成三類：第一類是","box":[[52,1350],[1734,1330],[1735,1412],[53,1432]]},{"text":"全訓部除，訓棘是主要的，這就是值班部除；二類是施工部隧；第三類是","box":[[54,1445],[1736,1424],[1737,1502],[55,1523]]},{"text":"全生產部除，搞生產是主要的，訓是附带的·晨副業生產在全軍的地","box":[[58,1543],[1736,1522],[1737,1591],[58,1612]]},{"text":"位提高了，成寫軍除主要任務之一。","box":[[68,1649],[889,1631],[890,1682],[69,1700]]},{"text":"盒什林總和軍委下這大的决心？照我的理解，還是一句老話，","box":[[158,1738],[1722,1717],[1723,1771],[159,1792]]},{"text":"就是需要與可能。國家整個情况來看需要這樣做，軍除生產供應來","box":[[65,1835],[1738,1809],[1739,1863],[65,1889]]},{"text":"看需要這樣做。我們國家连續年遭到了荒，晨業受到了破壤，有些","box":[[69,1932],[1740,1905],[1741,1954],[70,1981]]},{"text":"東西供應不上，要解决這個問题，在年之内主要是靠自己大搞晨副業","box":[[70,2025],[1740,1999],[1741,2050],[71,2076]]},{"text":"生產，這是需要。另一方面，軍除搞生產有了前雨年的生產基，部除","box":[[62,2113],[1745,2086],[1746,2148],[63,2175]]},{"text":"現在也可以負這個任務，這是因為我們有了值班部除，它什都不","box":[[68,2204],[1751,2177],[1752,2246],[69,2273]]},{"text":"翰，就是備打仗，一旦有事情，它可以頂一陣，所以其他部除就可以","box":[[64,2295],[1760,2266],[1761,2344],[66,2374]]},{"text":"搞生產了，這是可能。當然搞生產的部除也不是放下武器解甲歸田，而","box":[[64,2389],[1755,2359],[1756,2440],[66,2470]]},{"text":"是成建制的粗生座，也進行一定的訓。我們知道·古今中外軍除的","box":[[62,2477],[1761,2444],[1762,2538],[64,2570]]},{"text":"就帥，他們都是抵抓訓辣這一條，而我們就不是這檬·林德是既重部","box":[[64,2570],[1762,2538],[1763,2635],[66,2667]]},{"text":"除的訓，同時又把軍除晨副業生產的位置得很高，軍委和林魏這","box":[[58,2660],[1766,2629],[1768,2734],[60,2765]]},{"text":"决心，對我們管後勤工作的人來，是個可喜的好事，因為拿那多部","box":[[60,2751],[1770,2719],[1772,2831],[62,2863]]}],"dimensions":{"height":2880,"width":1815}}