{"ocr_results":[{"text":"第二章鞭門在家螂","box":[[234,10],[375,14],[374,31],[234,27]]},{"text":"15","box":[[582,18],[603,18],[603,35],[582,35]]},{"text":"第二章开在家鄉","box":[[185,140],[431,145],[431,170],[184,164]]},{"text":"第一次门","box":[[259,304],[363,306],[362,327],[258,325]]},{"text":"一九二九年初，紅軍主力離開興國一帶到東去开拓新區，一些地","box":[[68,338],[586,344],[586,364],[68,358]]},{"text":"方部也跟著出發了。還時興國以北泰和縣那的國民黛軍和靖活","box":[[28,368],[586,373],[586,394],[28,388]]},{"text":"動猖狂，經常向奥國蘇區、掠，形勢比较。蘇區緣地區的防","box":[[29,400],[585,405],[585,422],[29,417]]},{"text":"衡由當地的赤衛像和兒童图任，我們兒童國起了站放哨的任務，","box":[[28,430],[581,434],[581,451],[28,447]]},{"text":"监視泰和那人的動向，除了查路條之外，還要傅遮情報。","box":[[28,461],[508,463],[508,480],[28,478]]},{"text":"那時，我家鄉的背牡年乎全部都参加了赤衛除、少先除（十五崴以","box":[[65,491],[584,493],[584,511],[65,509]]},{"text":"上少年参加），適龄兒童都参加了兒童圈。為了保衛分得的田地和勝利果","box":[[29,521],[585,524],[585,541],[29,538]]},{"text":"寶，人民群累非常極。遣是人民戳争最初的萌芽。","box":[[29,553],[428,553],[428,570],[29,570]]},{"text":"村蘇埃指定我们的哨設在村外大路的隘口處：哨位就在原来放","box":[[68,583],[585,583],[585,600],[68,600]]},{"text":"關公像的茶亭裹。第一次夜裹放哨我確實有些害怕，幸村子裹有個","box":[[27,613],[584,611],[584,630],[27,631]]},{"text":"好移伴和我一起出哨，我瞻子就大多了。晚上在哨位上，小移件們高翼","box":[[27,642],[585,642],[585,662],[27,662]]},{"text":"地了好長時間的話，大家都是顽童，很是天真，時而用鬼神人，時","box":[[26,671],[585,670],[585,690],[26,691]]},{"text":"而起革命成功後的家鄉，充滿美好的憧憬，直到瞌睡得睁不開眼了，","box":[[26,701],[581,699],[581,719],[26,722]]},{"text":"大家就先後睡下，我第-一次放哨就這样完成了。兒童團放啃多流於形","box":[[26,731],[583,729],[583,750],[26,752]]},{"text":"式，但有了這種形式，人也多少有些害怕，這些小伴後來也大都参","box":[[26,762],[582,758],[582,778],[26,782]]},{"text":"加了紅軍，大都死在門中和長征路上，我算是一個存者。","box":[[26,789],[492,787],[492,810],[26,812]]},{"text":"兒童有-项任務，就是参加生產動。兒童團主要負了三種","box":[[64,821],[583,816],[583,836],[64,842]]},{"text":"晨活：一是放牛；二是肥；三是割飼草。忙中孩子們要做的事更不計","box":[[24,849],[582,845],[582,868],[24,872]]},{"text":"其數。那些男人上了前線的家庭·孩子的動更是辛苦，甚至成了主要","box":[[24,878],[582,874],[582,897],[24,901]]},{"text":"劳動力。管如此，兒童團還要持訓、站、放哨、宣傅等常规工","box":[[24,905],[581,903],[581,927],[24,929]]},{"text":"作。有一次，我們分除邀捉住了人一個值探，受到了區政府的樊。","box":[[23,935],[557,931],[557,956],[24,960]]},{"text":"方块字读书社区http://book.sinozi.cr","box":[[325,985],[620,985],[620,999],[325,999]]}],"dimensions":{"height":1001,"width":624}}