{"ocr_results":[{"text":"邱金作回憶錄","box":[[622,32],[916,14],[919,57],[624,76]]},{"text":"：：","box":[[371,151],[390,151],[390,161],[371,161]]},{"text":"携中央指示，增加了五十三人，包括业中央、國務院有關部委","box":[[70,259],[1619,216],[1622,323],[73,367]]},{"text":"和各中央局负贵同志，第一隋段未参加會的軍區、兵種、軍","box":[[67,353],[1619,307],[1622,411],[70,457]]},{"text":"事院校的負贵同志。第二段参加會的共九十五人。","box":[[84,478],[1304,417],[1306,471],[86,533]]},{"text":"由於三月十八日羅瑞卿跳樓自毅(受傷)，第二段的會，","box":[[178,535],[1577,490],[1580,584],[181,629]]},{"text":"张好又轉為背靠背的門爭。","box":[[76,664],[677,636],[679,682],[78,710]]},{"text":"，根攘會揭發的大量材料，羅瑞卿同志的主要錯误事實有如","box":[[70,721],[1617,677],[1619,766],[73,811]]},{"text":"下個方面：","box":[[83,845],[392,830],[395,877],[85,892]]},{"text":"第一，.視和反對毛澤東思想，和攻擎毛澤東同志。","box":[[181,910],[1491,865],[1493,942],[184,987]]},{"text":"羅瑞卿同志極端視毛澤東思想。林彪同志提出，要「把毛","box":[[179,995],[1620,955],[1622,1040],[181,1079]]},{"text":"主席的書当作我們全軍各项工作的最高指示，瑞卿同志胡","box":[[71,1092],[1621,1051],[1623,1131],[73,1172]]},{"text":"这「不符合我們國家的體制。林彪同志提出，「毛澤束思想是當代","box":[[69,1178],[1622,1141],[1624,1227],[71,1264]]},{"text":"最高最活的馬克思列寧主羲1，瑞卿同志胡，「不能這樣講，","box":[[75,1278],[1591,1239],[1593,1316],[77,1355]]},{"text":"最高，難道遗有次高的？難道不能再高了？最活，難道遗有次","box":[[75,1371],[1620,1336],[1622,1410],[77,1445]]},{"text":"活的？」「最高最活，不好理解，外國人也不好翻呀！林彪","box":[[74,1465],[1624,1431],[1626,1502],[76,1536]]},{"text":"同志提出，「毛澤東思想是當代馬克思列寧主羲的頂峰」，瑞卿","box":[[78,1560],[1622,1528],[1623,1595],[79,1627]]},{"text":"同志胡，「這句話也不要這樣，對外國人影響不好。」羅瑞","box":[[78,1655],[1622,1625],[1623,1689],[79,1718]]},{"text":"卿同志還不准毛澤東思想的形成包含有「個人天才」的因素，","box":[[78,1749],[1593,1720],[1594,1782],[79,1811]]},{"text":"什「現在没人敢再提個人天才了呀！林彪同志提出，「讀毛","box":[[81,1845],[1621,1819],[1622,1875],[81,1901]]},{"text":"主席的書，毛主席的話，照毛主席的指示瓣事，做毛主席的好","box":[[82,1942],[1623,1916],[1624,1967],[83,1993]]},{"text":"士」，羅瑞卿同志反對向外國人宣傅和介绍這四句話。林彪同","box":[[81,2036],[1621,2013],[1621,2063],[81,2087]]},{"text":"志指示《解放軍報》要經常刊载《毛主席語錄》，瑞卿同志嫌","box":[[81,2130],[1625,2108],[1625,2160],[81,2182]]},{"text":"搞多了。總政治部根據林彪同志的指示，把毛主席、中央的指","box":[[82,2221],[1627,2204],[1628,2258],[82,2275]]},{"text":"示和軍委的文件，成教材，作為幹部、士的必修課，瑞卿","box":[[82,2317],[1626,2298],[1627,2353],[83,2373]]},{"text":"同志借口發到連隧的東西太多了，不准印發。林彪同志指示，","box":[[83,2409],[1598,2396],[1599,2456],[84,2469]]},{"text":"要在民兵中開展學習毛主席著作的活動，瑞卿同志胡，「不","box":[[83,2503],[1631,2488],[1632,2548],[84,2564]]},{"text":"要單獨給民兵怖置學習毛著任務j。羅瑞卿同志遗指歌舞劇《水","box":[[81,2594],[1633,2580],[1634,2648],[81,2663]]},{"text":"兵的光榮》中，唱「敬愛的毛主席」太多了，要和共產聯繁","box":[[78,2685],[1641,2674],[1642,2750],[79,2761]]},{"text":"起來，不要單獨地唱。","box":[[88,2784],[566,2789],[565,2840],[87,2834]]},{"text":"羅瑞卿同志歪曲和反對毛主席關於級和隋級門爭的理论，","box":[[189,2875],[1605,2869],[1605,2941],[190,2947]]},{"text":"毛主席一再教導，人民内部也有隋級矛盾，羅瑞卿同志胡，","box":[[81,2964],[1611,2960],[1611,3042],[81,3046]]},{"text":"「農民有一部分自發勢力，想搞單干，不是隋級矛盾，而是人民内","box":[[71,3054],[1649,3050],[1649,3143],[71,3147]]}],"dimensions":{"height":3160,"width":1697}}