{"ocr_results":[{"text":"邱會作回憶錄","box":[[754,34],[1030,21],[1031,56],[755,69]]},{"text":"468","box":[[45,77],[126,73],[128,118],[47,122]]},{"text":"小打攀面。不能懂根據是否衡攀遗军事机阑这一點來制分左、","box":[[190,227],[1682,208],[1683,336],[192,355]]},{"text":"中、右。","box":[[209,366],[382,358],[384,411],[212,419]]},{"text":"(五）對待较大的群显组织探取什座態度，应就地深入调查研","box":[[290,385],[1713,373],[1714,501],[291,513]]},{"text":"究，进行級分析；探取重大行動前，愿向中央文革和全军文革","box":[[180,477],[1715,452],[1717,583],[182,608]]},{"text":"請示報告。","box":[[199,622],[420,608],[424,655],[202,670]]},{"text":"（六）一概不要進行群景性的「請罪」课動。也不要強迫群","box":[[288,648],[1715,626],[1717,746],[289,767]]},{"text":"寫检讨。群最自寫的检讨書，退遣其本人。有些长期不觉悟亚","box":[[174,738],[1719,709],[1721,832],[176,861]]},{"text":"且持錯误觀點的群，不要急於要他們錯，而要給以時間，","box":[[173,833],[1691,798],[1694,909],[175,943]]},{"text":"镰他們在門爭中自己教育自己。不允許體和相體。例如，","box":[[171,923],[1695,888],[1697,995],[174,1030]]},{"text":"戴高帽，黑牌，游街，跪，等等。","box":[[184,1048],[1046,1002],[1049,1059],[187,1105]]},{"text":"(七）在軍隧中要深入進行以毛主席為代表的无産級革命","box":[[276,1098],[1724,1068],[1726,1169],[278,1198]]},{"text":"路線同资產級反动路線的雨條路線門爭的教育。學習毛主席著","box":[[165,1193],[1728,1156],[1731,1259],[167,1296]]},{"text":"作，必须结合雨條路線的門爭。廣泛搜集揭露反動路線和一小撮","box":[[161,1287],[1729,1248],[1732,1347],[164,1386]]},{"text":"黛内走资本主羲道路当權派的各種具體材料，印發到連隙進行教","box":[[162,1382],[1732,1343],[1734,1434],[165,1473]]},{"text":"育，使廣大指員瞭解他們的反動事實，進行徹底批判，清其","box":[[161,1475],[1732,1435],[1734,1524],[163,1564]]},{"text":"惡劣影響。","box":[[171,1595],[396,1583],[399,1635],[174,1647]]},{"text":"對派到地方上去或主持支左的斡部，要細交待政策。","box":[[401,1663],[1700,1630],[1702,1698],[403,1731]]},{"text":"（八）当","box":[[286,1682],[435,1682],[435,1730],[286,1730]]},{"text":"要防止趟永夫式的反革命分子（趙永夫原青海省軍區副司令員，是","box":[[161,1764],[1737,1721],[1739,1794],[163,1837]]},{"text":"一個混進黛内軍内的反革命分子，他玩弄陰谋手段，篡奪軍權,","box":[[162,1861],[1706,1819],[1708,1884],[164,1926]]},{"text":"對革命群組織進行残酷的武装鎮壓）或思想很右的人來主持支","box":[[161,1958],[1738,1914],[1740,1977],[163,2022]]},{"text":"左工作。","box":[[159,2061],[340,2052],[343,2111],[161,2119]]},{"text":"（九）在支左工作中，要學會做群工作，相信群，依靠群","box":[[278,2152],[1745,2107],[1747,2161],[280,2205]]},{"text":"，有事同群商量，善於探用服教育的方式，而不應探取簡","box":[[165,2253],[1747,2203],[1749,2257],[166,2307]]},{"text":"單粗暴和命令的方式。","box":[[165,2351],[658,2337],[659,2385],[166,2400]]},{"text":"（十）對業已反了上述诸條做法的，都要立即改正，極進","box":[[275,2442],[1754,2396],[1756,2450],[277,2497]]},{"text":"行善後處理。今後，决按以上各條瓣事。","box":[[163,2545],[1178,2517],[1179,2566],[164,2594]]},{"text":"這個命令，要在我軍所有機關、連隧内部用電報、電話迅速","box":[[269,2633],[1767,2581],[1770,2646],[271,2698]]},{"text":"傅達，廣泛張貼。","box":[[164,2737],[554,2729],[555,2780],[165,2789]]},{"text":"十","box":[[1564,2828],[1581,2828],[1581,2836],[1564,2836]]},{"text":"之","box":[[1578,2828],[1595,2828],[1595,2836],[1578,2836]]}],"dimensions":{"height":2844,"width":1800}}