{"ocr_results":[{"text":"邱鑫作回憶錄","box":[[640,83],[885,55],[889,90],[644,119]]},{"text":"606","box":[[60,165],[122,161],[125,198],[62,202]]},{"text":"林總的長篇講话","box":[[595,293],[974,256],[979,306],[600,343]]},{"text":"十二中全含期相，林液装装丁能篇满活、林施的南品印有能结稿、","box":[[142,343],[1534,299],[1539,470],[147,515]]},{"text":"市、各大軍區都發一盤·亚在群中播放。","box":[[81,598],[897,514],[901,556],[85,640]]},{"text":"林德在講話中説：","box":[[163,665],[487,633],[491,676],[167,709]]},{"text":"现在我要读的罚题，有以下六點：第一個，就是文化革命的","box":[[220,666],[1500,631],[1503,770],[223,806]]},{"text":"必要性：第二假，是文化革命的腾利、意羲和它在世界愿史上的","box":[[130,753],[1500,712],[1505,851],[134,892]]},{"text":"地位；第三衢，就是文化革命的路练、做法的御题；第四個、是","box":[[128,834],[1502,799],[1506,935],[131,970]]},{"text":"主席對属列主羲的偉大发展，特别是在社會主羲條件下革命怎样","box":[[123,920],[1498,885],[1501,1011],[126,1046]]},{"text":"灌续前造的岗题；第五個，是中國革命和世界革命；第六個，是","box":[[128,1004],[1497,973],[1500,1098],[131,1129]]},{"text":"今後怎做法。","box":[[145,1141],[405,1123],[409,1170],[148,1188]]},{"text":"林在講到：","box":[[141,1220],[374,1203],[378,1255],[144,1272]]},{"text":"我要到中國无產級文化革命在世界文化革命中間的歷史地位。","box":[[126,1262],[1500,1236],[1502,1340],[128,1366]]},{"text":"要一講，才能着出我們這次的文化革命是人類有史以来的最大最廣及","box":[[34,1349],[1522,1324],[1523,1429],[35,1454]]},{"text":"的最有深速意羲的革命。祗有通过比我們才能看得出它是最广泛，是","box":[[35,1437],[1522,1416],[1523,1509],[36,1529]]},{"text":"最深入，是最能影響人類歷史進程和影響中國今後的命運的。","box":[[43,1543],[1269,1512],[1271,1574],[44,1605]]},{"text":"林説：","box":[[128,1628],[292,1622],[294,1680],[130,1686]]},{"text":"在我看，世界上的歷史，在世界上有重大影響的文化革命，","box":[[215,1706],[1453,1694],[1454,1753],[215,1764]]},{"text":"大致可以有四大次，有四次。","box":[[133,1801],[664,1794],[665,1841],[134,1848]]},{"text":"第一次，希、羅馬的古典文化，在公元以前五世紀、四世","box":[[215,1882],[1478,1878],[1478,1928],[215,1931]]},{"text":"紀，希的奴制度是處於繁盛的時代，希的古典文化，也處","box":[[129,1966],[1478,1965],[1478,2014],[129,2016]]},{"text":"於這種那個时候出現了影響全世界上雨千多年來的思想，那是希","box":[[124,2051],[1478,2053],[1478,2107],[124,2105]]},{"text":"、羅马的古典文化。那時出現了德莫克里特、赫拉克里德、亞","box":[[121,2132],[1483,2139],[1483,2202],[121,2195]]},{"text":"里斯多德、伯拉圆、蘇格拉底、伊壁鸠鲁，他們是影響整個歐洲","box":[[122,2217],[1484,2225],[1484,2295],[122,2286]]},{"text":"的文化，也影響後來中國的思想。但是，那種文化是為奴主瓣","box":[[112,2296],[1490,2308],[1489,2389],[111,2378]]},{"text":"的文化。这個是奴藜制度的文化，同我們的文化革命比那就是","box":[[109,2381],[1490,2395],[1489,2480],[108,2466]]},{"text":"微不足道了，有一旬话叫什，就是小巫见大巫吧。看到我們的","box":[[109,2463],[1491,2481],[1490,2575],[108,2557]]},{"text":"文化革命運動才知道是大巫，知道它那個是小巫。而没有這個比","box":[[110,2541],[1498,2563],[1496,2672],[109,2649]]},{"text":"较的時候，我們腦子凳得，它那個了不得，但實際上同我們的一","box":[[106,2630],[1497,2654],[1495,2761],[104,2737]]},{"text":"比，它那個没有什磨了不得。","box":[[124,2731],[672,2765],[670,2812],[121,2778]]},{"text":"方块字读书社区制作","box":[[1191,2752],[1412,2749],[1412,2776],[1192,2779]]}],"dimensions":{"height":2852,"width":1566}}