{"ocr_results":[{"text":"邱會作回憶錄","box":[[681,60],[916,43],[919,77],[683,94]]},{"text":"698","box":[[113,109],[176,106],[178,145],[115,148]]},{"text":"映汝（微平了上海命，道是食天之功色己有·：稳能","box":[[99,426],[1529,438],[1528,602],[98,590]]},{"text":"恢十·不是装春吹的辨候好·是在毛主席同意约情况下·把我","box":[[100,506],[1526,516],[1524,673],[99,663]]},{"text":"春大的到立面复愿下去的·上海的文化大基命是花了很大代德的·中唤","box":[[95,583],[1522,595],[1521,749],[93,736]]},{"text":"麦持：又尤肝醒·哪有摘不好之理另外，陈伯候了張春插参加","box":[[91,663],[1518,673],[1517,822],[90,812]]},{"text":"「九大」修改戴章就到處吹嘘自己，我寫的文章很多，我來都不。","box":[[95,765],[1451,758],[1451,869],[95,876]]},{"text":"此外，伯蓬還满了張春橘的許多話，有的我就記不起來了。","box":[[188,847],[1430,843],[1430,939],[188,944]]},{"text":"，我們大家在一起陳伯蓬講到二十四日早上三時，吃了夜餐。","box":[[153,929],[1388,924],[1388,1012],[154,1018]]},{"text":"我回到宿舍之後，劉秘書同我：「張池明政委、张合彬副部長，今","box":[[178,990],[1499,1006],[1498,1115],[176,1099]]},{"text":"，天下午來看部長了。我即想到要給他們回個電話，否则，他們會有意見","box":[[48,1074],[1497,1088],[1496,1193],[47,1178]]},{"text":"的·但什呢？我稍微想了一下，就向他們回電話：「對林副主席的","box":[[82,1155],[1492,1173],[1491,1269],[80,1251]]},{"text":"語·可能還要粗藏錄音，這樣便於小組會上發言·這是個極其一般","box":[[82,1236],[1491,1256],[1490,1348],[80,1328]]},{"text":"的電話，我當時根本没有想到是搞什「陰課」，是想到給他們一點可","box":[[74,1320],[1485,1343],[1483,1424],[72,1401]]},{"text":"以的「内情」但後來追個不停，大家都知道，兩张在政治門争中，是","box":[[84,1402],[1483,1427],[1481,1502],[82,1477]]},{"text":"起不到多大作用的。·：","box":[[89,1506],[559,1502],[559,1548],[90,1552]]},{"text":"整個山都狂热起來","box":[[515,1670],[995,1679],[994,1728],[514,1719]]},{"text":"三十四日上午九時許，在山小禮堂林德罐話的錄音，毛主席昨","box":[[168,1758],[1465,1791],[1464,1835],[166,1802]]},{"text":"天晚上就同意林彪講話錄音·除毛主席·林總之外，中央常委、政治","box":[[68,1832],[1466,1868],[1465,1921],[67,1885]]},{"text":"局委員全部到場了，元們也來了·江青這個向來「自由自在：活動的人","box":[[70,1907],[1466,1947],[1464,2010],[68,1971]]},{"text":"也來了，坐在第一排中央·她的行動就可看出林總話對江青的震動","box":[[69,1987],[1468,2028],[1466,2093],[67,2053]]},{"text":"有多大！如果不是這樣的話，郎使出子抬也是抬不來她的·錄音放了","box":[[59,2065],[1467,2106],[1465,2180],[57,2139]]},{"text":"通以後，理再放一遍。中央委員們了林彪三次講話（上午了","box":[[98,2140],[1471,2182],[1468,2267],[95,2225]]},{"text":"兩逼錄音）·已經消化得差不多了。大家錄音這件事，就知道要毅","box":[[46,2215],[1473,2259],[1470,2356],[43,2311]]},{"text":"曾表態和怎应表態了·於是大家粉在小組會上發言，表示摊護林能的","box":[[44,2296],[1473,2339],[1470,2439],[41,2396]]},{"text":"請道也是顺理成草的事·汪東奥和陳伯達在華北組都發了言，尤其","box":[[36,2367],[1480,2415],[1476,2530],[32,2482]]},{"text":"是在東典的教言勤了整個全會，汪束興在發言中提出揪人是發言的要","box":[[37,2446],[1480,2493],[1476,2615],[33,2567]]},{"text":"青之道·随著注東和陳伯逢的發育及随後出的北組的鳞!","box":[[32,2522],[1487,2566],[1483,2700],[28,2656]]}],"dimensions":{"height":2735,"width":1555}}