{"ocr_results":[{"text":"邱會作回憶錄","box":[[700,52],[931,42],[933,75],[702,85]]},{"text":"754","box":[[133,90],[197,86],[199,123],[136,127]]},{"text":"·","box":[[1222,114],[1283,120],[1281,134],[1221,128]]},{"text":"Y","box":[[24,151],[44,151],[44,158],[24,158]]},{"text":"解终我自己的橡计报合脚题，在氧参能策拿的时候，我就前的了～","box":[[227,183],[1525,216],[1521,368],[223,335]]},{"text":"而忽变，一是和陈伯逢的關保·我同障信涂报本设有愿生","box":[[121,400],[1527,436],[1523,589],[117,552]]},{"text":"独工作脚保·六七午夏天才同他面對面第一次铁远。我展什费能间绝指","box":[[117,477],[1522,512],[1519,656],[114,621]]},{"text":"在一起呢？最主要是迷信他是「大理输家」，有就是對振春椅不满有共","box":[[114,555],[1519,587],[1516,727],[111,695]]},{"text":"同犯自由主義的關係，陈伯逢是大骗子，他骗了我道樣的人，我又把德","box":[[111,632],[1514,665],[1511,797],[108,765]]},{"text":"摘的「器錄在小粗上宜，我既是上當者，又是受害者，遵是害人者;","box":[[110,717],[1502,744],[1500,863],[108,836]]},{"text":"二是和腰春橘的關係間题。我同張春橋雄然没有争吵過，但不来往，不","box":[[108,791],[1507,823],[1505,940],[106,909]]},{"text":"接近。陳伯達就把我當作他反對張春橘的同盟軍了。","box":[[114,916],[1099,902],[1100,952],[114,966]]},{"text":"我的报告寫好後，於七一年三月中旬就送給周德理·總理看到报告","box":[[189,950],[1498,984],[1495,1085],[186,1051]]},{"text":"之後，怠寫得不錯·他很高興·他轉給了毛主席。","box":[[112,1069],[1092,1063],[1092,1105],[112,1111]]},{"text":"毛主席第一次接見","box":[[571,1219],[987,1224],[986,1272],[571,1267]]},{"text":"毛主席收到黄永勝·李作鹏和我的讨報告，很快就批了下來·主","box":[[181,1292],[1484,1327],[1482,1402],[179,1366]]},{"text":"席的批示是：「黄永勝、邱會作·李作鹏三同志的讨都看了，我寫","box":[[94,1372],[1481,1409],[1479,1477],[92,1440]]},{"text":"得很好。以後是實這些申明的問題。其實，我們的讨寫得一般，但","box":[[90,1456],[1475,1493],[1474,1550],[89,1513]]},{"text":"满足了毛主席的心。","box":[[93,1545],[487,1553],[486,1593],[92,1585]]},{"text":"一九七一年三月二十四日下午三时，毛主席在中南海住處和周","box":[[175,1621],[1469,1655],[1467,1701],[174,1668]]},{"text":"理、康生接見了黄永勝、吴法崽、李作鹏、邱會作、紀登奎、李德生，","box":[[86,1699],[1457,1739],[1456,1781],[85,1741]]},{"text":"汪東興。","box":[[85,1777],[262,1777],[262,1818],[85,1818]]},{"text":"毛主席是在他的卧室接見我們六個人的，主席坐在沙發上，向我們","box":[[160,1853],[1468,1893],[1466,1948],[158,1907]]},{"text":".","box":[[139,1868],[173,1868],[173,1883],[139,1883]]},{"text":"進去的人微笑招手·我們進去的人都先向主席敬禮、握手，然後在兩旁","box":[[73,1923],[1469,1968],[1467,2031],[71,1987]]},{"text":"坐下·我們坐好之後，毛主席：「早就要請你們位來，今天才實","box":[[67,1997],[1470,2046],[1468,2118],[64,2068]]},{"text":"现。中國人有句話叫做；禮多人不怪，有禮不怕。毛主席總是带著笑","box":[[60,2069],[1474,2121],[1471,2202],[57,2151]]},{"text":"容話的·正在話時，毛主席忽然想到：「馬什不叫汪東興來呀？","box":[[62,2149],[1476,2201],[1473,2284],[59,2231]]},{"text":"回兒江東奥來到了","box":[[103,2240],[564,2271],[562,2312],[100,2280]]},{"text":"毛主席：中央维備召一次會。主要内容是批陳整風問题，","box":[[141,2308],[1465,2355],[1462,2449],[137,2401]]},{"text":"你們之中的一些同志也發言做點自我批，名義上陳伯達的問題，","box":[[46,2376],[1458,2433],[1454,2534],[42,2477]]},{"text":"實際上給你們做點自我批創造條件，這樣做好不好？！","box":[[58,2467],[1130,2543],[1126,2596],[54,2520]]},{"text":"方块字读书社区制作","box":[[1190,2547],[1412,2545],[1412,2571],[1190,2573]]}],"dimensions":{"height":2647,"width":1565}}