{"ocr_results":[{"text":":","box":[[27,5],[43,5],[43,17],[27,17]]},{"text":"「甩石頭掺沙子挖精脚」","box":[[632,14],[1029,22],[1028,54],[631,45]]},{"text":"第三十四章","box":[[377,36],[566,20],[569,52],[380,68]]},{"text":"763","box":[[1383,37],[1452,41],[1450,75],[1381,71]]},{"text":"：.","box":[[1169,79],[1239,79],[1239,96],[1169,96]]},{"text":"W","box":[[303,98],[437,85],[439,104],[305,117]]},{"text":"德理完全同意了黄永腾的建，於四月十四日在會论的预偏价上，","box":[[129,198],[1415,159],[1419,282],[133,322]]},{"text":"周德理對毛主席的指示傅得很详細·發押得也很好，大多数人","box":[[129,410],[1436,378],[1439,495],[132,527]]},{"text":"的指示。","box":[[82,420],[201,388],[211,429],[93,460]]},{"text":"完经捕薄理的傳逢，對會着起到了鱼要作用·我們到毛主席的","box":[[61,484],[1444,435],[1449,570],[65,618]]},{"text":"数示是门争的「武器」亚不是過隔的「通行證」。抵有拿起武器坚决门争","box":[[63,560],[1434,514],[1438,638],[67,684]]},{"text":"能過得去这一關。","box":[[86,686],[403,640],[409,683],[92,729]]},{"text":"黄永勝在軍委瓣事組召集與會人員的會上：「今年二月間軍委座","box":[[131,704],[1448,681],[1450,779],[132,802]]},{"text":"食，我們愿当向大家做讨·但没有這样做·這是我們的錯误，我代表","box":[[62,780],[1454,745],[1457,855],[65,890]]},{"text":"重委辨事粗在山犯了錯的同志，向大家承昭錯！今天，我向大家做","box":[[68,856],[1457,825],[1459,928],[71,958]]},{"text":"梭計，傅蓬毛主席的指示。在三月底四月初毛主席連續接見了軍委瓣","box":[[69,933],[1457,904],[1459,1000],[70,1028]]},{"text":"事組雨次·参加接見的有：黄·吴、李、邱丶紀、李等六人·我的傅蓬，","box":[[70,1011],[1447,983],[1449,1071],[71,1099]]},{"text":"如有遗漏的，他們可以補充。」黄永勝對毛主席的指示，傅達得很详細。","box":[[73,1087],[1445,1066],[1447,1145],[74,1166]]},{"text":"擦到會的人後來，這次傅達，對統一思想真正起到了重要作用。","box":[[72,1166],[1317,1146],[1318,1218],[73,1238]]},{"text":"批陳整風匯報會的思想備是很充分的，江青一的抵制力量也是","box":[[138,1242],[1456,1232],[1456,1293],[139,1304]]},{"text":"很強的·這也就是們争是非常激烈的·軍委瓣事組「恪守批示」，江","box":[[73,1320],[1460,1309],[1461,1371],[73,1381]]},{"text":"青一移！先露锋芒」。","box":[[75,1404],[431,1397],[432,1445],[76,1451]]},{"text":"‘這次中央的會，名義上是批陳整風，實際上是和江青一的较","box":[[80,1476],[1458,1471],[1458,1522],[80,1527]]},{"text":"量·到會人數不足百人，就其政治情况來，護軍委辦事組的人約三","box":[[69,1554],[1456,1551],[1456,1596],[69,1599]]},{"text":"分之二：摊護江青一的三分之一不到。由於會是「結束虚山會」的","box":[[74,1630],[1458,1631],[1458,1676],[74,1675]]},{"text":"會：因此整個會過程都門争得很激烈。門争的主要問題是對會的","box":[[69,1704],[1460,1710],[1460,1758],[69,1751]]},{"text":"方向封小組會的控制和對吴法患的追擎三個問題。","box":[[59,1775],[1055,1789],[1054,1840],[59,1826]]},{"text":"會開始讨的是什問題，這就是是會的方向。四月十四日晚","box":[[135,1853],[1467,1862],[1466,1919],[135,1911]]},{"text":"上：政治局會查中央工作會的弹備情况時，發現已經印發的文件，","box":[[58,1925],[1460,1938],[1459,2003],[58,1991]]},{"text":"概有黄·臭葉、李、邱的讨報告，批陈整風的文件一份也没有印","box":[[61,1994],[1471,2012],[1470,2087],[60,2070]]},{"text":"發·樣·會很自然就會批「黄」（黄·吴·葉、李、邱）開始·而","box":[[55,2066],[1474,2089],[1473,2171],[53,2148]]},{"text":"不會推“陳（陈伯達）開始了。會批判的目標變了，而也就會影","box":[[56,2142],[1477,2163],[1476,2249],[54,2228]]},{"text":"會藏的方向。：","box":[[66,2227],[366,2250],[362,2299],[62,2275]]},{"text":"周德理發现了过個間題，他著急了，總理問張春橋：「什应不先","box":[[122,2300],[1478,2320],[1477,2406],[121,2386]]},{"text":"即毅出澳的文件，而抵印發他們的讨报告？現在立即提印商件，","box":[[46,2360],[1473,2393],[1471,2495],[44,2463]]}],"dimensions":{"height":2524,"width":1561}}