{"ocr_results":[{"text":"第三十八章在顺羲的日于裹","box":[[424,6],[958,0],[959,29],[425,43]]},{"text":"825","box":[[1396,0],[1464,1],[1463,24],[1395,22]]},{"text":"..","box":[[1127,45],[1534,36],[1535,57],[1128,66]]},{"text":"在衡成區我穿的還是按軍除的供應標發衣服的·在五年多的時間","box":[[88,214],[1424,157],[1427,237],[91,294]]},{"text":"裹，七一年冬天給我發過一套新棉衣。七二年春天，還我做過兩件翩","box":[[24,291],[1430,223],[1435,318],[28,386]]},{"text":"的確良概衣·對穿衣没有發生避困難，日常用品也没有發生過困難·看","box":[[29,365],[1430,302],[1434,393],[33,455]]},{"text":"管組的人，看到我需要了什应東西，總是主動同我買來了，他們對我的","box":[[30,441],[1431,376],[1435,466],[34,531]]},{"text":"生活考得很周到。","box":[[46,545],[373,510],[378,554],[51,588]]},{"text":"，七三年的國慶期間，師長來到我的住處問我：「你為什色也不","box":[[65,592],[1431,546],[1433,611],[68,658]]},{"text":"好·是否管養不？其實我對生活是满意的。","box":[[41,681],[902,629],[906,691],[45,743]]},{"text":"可是；第二天中午不到，看管組的人提回來了一箭子活·晚飯就","box":[[102,741],[1437,699],[1439,764],[104,806]]},{"text":"：","box":[[91,776],[111,776],[111,790],[91,790]]},{"text":"打來了一碗湯和適量的肉·打飯的人關心地：「好好吃吧，多吃一","box":[[40,818],[1439,767],[1441,844],[43,895]]},{"text":"點：長胜一點。以後就接連天晚上都有一碗湯。","box":[[48,903],[1045,858],[1048,918],[51,963]]},{"text":"一天：我問對我特别同情的防化連H副連長：「現在伙食已經改善","box":[[78,971],[1438,933],[1440,989],[80,1027]]},{"text":"了什每天都有肉吃？」他很奇的回答：「啊；你還不知道呀！","box":[[45,1050],[1447,1002],[1450,1066],[48,1114]]},{"text":"這是我们師長特别鳥你改善伙食的，要把你的身體搞好….·我：「現","box":[[52,1124],[1446,1081],[1448,1144],[54,1186]]},{"text":"在我不是好好的？總理還會有什批？」H副連長：「我們師長最","box":[[53,1200],[1447,1160],[1448,1220],[55,1259]]},{"text":"近到中央去開過一次會，主要是讨你們出路的問題·到什地方去，","box":[[54,1277],[1438,1239],[1440,1295],[56,1333]]},{"text":"什時侯出去都還没有定下來·周總理有指示，要注意你們的生活，不","box":[[51,1355],[1450,1318],[1451,1371],[52,1408]]},{"text":"要搞得很難看·這就是給你加強營養的原因。你要能吃下去就放開","box":[[54,1430],[1452,1392],[1454,1448],[56,1487]]},{"text":"吃·我们師裹晨場東西也多得很…·····","box":[[55,1507],[780,1492],[781,1538],[56,1553]]},{"text":"生活問題之二·醫療問題，師長也是很關心的問題。","box":[[130,1582],[1134,1562],[1135,1606],[130,1627]]},{"text":"為我看病的醫生是師醫院門診部主任。開始的時候，他的工作","box":[[129,1660],[1454,1631],[1455,1677],[131,1706]]},{"text":"位是專門招呼我的同我住在一起，對我非常好。我這個會經的總後","box":[[64,1735],[1459,1705],[1460,1754],[65,1784]]},{"text":"勤部長全軍基唇的醫務力量不足是瞭解的，我個人的病情量竟是不多","box":[[61,1815],[1458,1790],[1459,1829],[61,1853]]},{"text":"的·於是：我對師長把他的工作方法改缦了一下，白天仍到門診所去","box":[[65,1891],[1461,1865],[1462,1907],[65,1932]]},{"text":"上班晚上同我住在一起，白天對我则隨叫隨到，師長同意了。","box":[[66,1966],[1271,1947],[1272,1989],[66,2008]]},{"text":"了治病，我用藥是非常方便的，乎要什藥都有，後來我才知","box":[[134,2043],[1467,2022],[1468,2064],[134,2085]]},{"text":"道，中央保健小組同那位主任有直接的工作關係·贵重的藥品随時可以","box":[[58,2114],[1470,2098],[1471,2147],[59,2163]]},{"text":"要來高明的醫生随時可以請來。七二年初，在澡塘洗澡我不慎在室内","box":[[71,2196],[1472,2176],[1473,2222],[72,2242]]},{"text":"跌了一下·当時很疼，兩小時内北京醫院的外科專家就來到我的住處，","box":[[69,2266],[1467,2253],[1468,2305],[69,2318]]},{"text":"為我看病·医生對我的健康也非常注意，每月至多三個月要給查一次","box":[[72,2345],[1481,2330],[1482,2382],[73,2397]]},{"text":"身體還注射過胎盤球蛋白·衡戌區對我的醫療，我同樣是十分滿意","box":[[71,2418],[1485,2406],[1486,2462],[72,2475]]},{"text":"方块字读书社区制作","box":[[1168,2494],[1387,2494],[1387,2519],[1168,2519]]}],"dimensions":{"height":2594,"width":1541}}