{"ocr_results":[{"text":"第四十二章移交高检與预骞","box":[[464,17],[1032,30],[1031,75],[463,62]]},{"text":"911","box":[[1460,75],[1526,78],[1524,117],[1458,114]]},{"text":"邈交超蓄後的當天下午三時，有两個人到监房來同我話。「今天","box":[[97,218],[1497,233],[1496,349],[96,334]]},{"text":"怎樣：感覺如何？」监管員先話。","box":[[34,350],[738,299],[743,375],[40,426]]},{"text":"《大姑娘上，頭一次·我心中無愧，不怕見間王，何况今天見的","box":[[82,389],[1495,399],[1494,504],[81,494]]},{"text":"是小鬼」","box":[[36,529],[196,511],[202,562],[42,580]]},{"text":"「你可以你的真實的思想。」","box":[[99,584],[761,567],[762,628],[101,645]]},{"text":"「我對腿書的印象是，寫起诉書的人不是實事求是的·","box":[[85,649],[1309,653],[1309,731],[85,728]]},{"text":"南央是會有正確决策的！","box":[[98,753],[663,740],[664,788],[99,801]]},{"text":"現在世道不同了，一切都燮了!毛主席丶周總理要是健在，根本","box":[[123,816],[1491,824],[1491,895],[123,887]]},{"text":"不前能毅生公的事。當然，現在自已要面對公密了，我還是要向毛主","box":[[36,902],[1495,896],[1496,978],[36,984]]},{"text":"席教的，我想起了毛主席長期教育我的兩句話，即一不怕苦，二不怕","box":[[36,992],[1492,986],[1492,1053],[36,1059]]},{"text":"死今天對我特别有用處·我就以這兩句話去對待公！","box":[[39,1080],[1196,1072],[1196,1132],[39,1140]]},{"text":"我粗略翻了一下。我對起诉書本身的感覺就是一頓，起書","box":[[125,1164],[1485,1161],[1486,1213],[125,1216]]},{"text":"開頭就寡的什，“以推翻無產皆級專政自的，，這樣的帽子扣在任何人","box":[[45,1252],[1481,1244],[1481,1288],[45,1296]]},{"text":"頭上都必死無疑！也奇怪，在文化大革命中，因為我在臺上工作就是推","box":[[45,1333],[1481,1327],[1481,1372],[45,1378]]},{"text":"翻無產楷級專政？我真的很痛心。出毛主席的氣，方法多得很，怎座非要","box":[[41,1414],[1485,1405],[1486,1458],[42,1467]]},{"text":"這搞呢？J","box":[[45,1491],[276,1499],[274,1549],[43,1540]]},{"text":"：交起書後的第五天，最高法院來的三個人，主持谈話的人，","box":[[70,1571],[1487,1558],[1488,1629],[71,1642]]},{"text":"經陪同萬毅來同我過話，後來是公密的法官·另一個是許宗琪，原總","box":[[38,1646],[1491,1634],[1491,1717],[39,1729]]},{"text":"後政治部文化部副部長，公密時的法官·另一個人别人种他吴老·谈話","box":[[29,1726],[1490,1711],[1491,1801],[30,1816]]},{"text":"時間，从上午八時開始到晚上十时才結束。","box":[[41,1812],[910,1826],[909,1894],[40,1880]]},{"text":"他們首先確了我不要律師後，主持人接著：「現在谈一個與公","box":[[59,1889],[1488,1870],[1489,1964],[60,1983]]},{"text":"有關的問題。","box":[[49,1973],[344,2004],[338,2053],[43,2021]]},{"text":"一意一年九月六日，李作鹏武漢回來，同你谈了毛主席南巡的開","box":[[39,2035],[1495,2019],[1496,2140],[40,2156]]},{"text":"惠所内容，你以前已經交代了，若没有新的内容就不必了·现在","box":[[19,2113],[1496,2094],[1497,2222],[20,2240]]},{"text":"主要一下，他同你谈的背景是什座？","box":[[38,2204],[839,2233],[836,2316],[35,2287]]},{"text":"我：「你們的背景指的是什？我不理解其意。」","box":[[98,2292],[1176,2287],[1177,2382],[99,2386]]},{"text":"我們間的是李作同你的目的是什座？","box":[[130,2376],[1002,2383],[1002,2466],[130,2459]]},{"text":"毛主席的指示都想疏解，更想瞭解毛主席對处山间题有無新的指","box":[[123,2448],[1479,2404],[1483,2521],[127,2566]]},{"text":"你們到毛主席南巡的指示聚張？","box":[[135,2615],[909,2626],[908,2701],[134,2690]]},{"text":"方块字读书社区制作","box":[[1201,2664],[1423,2664],[1423,2691],[1201,2691]]}],"dimensions":{"height":2765,"width":1575}}