{"ocr_results":[{"text":"第五章苦的月","box":[[210,14],[347,13],[347,30],[210,31]]},{"text":"73","box":[[555,10],[577,10],[577,27],[555,27]]},{"text":"减在川西，的狂言。面對人的强大壓力，紅軍内部分裂的氣氛一時被掩","box":[[7,93],[560,80],[561,107],[7,119]]},{"text":"了。","box":[[7,128],[56,125],[57,143],[9,147]]},{"text":"過草地","box":[[256,179],[318,179],[318,196],[256,196]]},{"text":"新的情追使紅軍要通過草地無人區，向甘的夏河流域前進。那","box":[[49,215],[563,208],[564,229],[49,236]]},{"text":"時我們面臨著兩個重困：草地恶劣的自然條件和人的追堵，前者甚","box":[[11,244],[565,235],[566,259],[11,268]]},{"text":"於後者。草地不没有人煙、食、道路，還有不少地段是沼澤（也叫水","box":[[11,274],[564,263],[565,287],[11,297]]},{"text":"草地），人根本不能走。","box":[[15,306],[195,301],[195,318],[15,323]]},{"text":"紅軍到了毛兒後就開始作遍草地的弹：這時周副主席患病了，","box":[[50,332],[563,325],[564,345],[50,352]]},{"text":"持續發高燒（多年後周恩來他得的是肝腰），大家都很心、我們把","box":[[15,363],[568,354],[569,375],[15,384]]},{"text":"架鋪的很软，勤換架員，這樣就平穗多了，我忙完工作、也去周","box":[[15,393],[567,383],[568,403],[15,413]]},{"text":"恩來抬架，我嫌架鼻走的不穗·衛生所長王斌是周恩來治病的醫","box":[[17,422],[567,412],[568,432],[17,442]]},{"text":"生，有醫藥和器械，他唯一能探取的瓣法是要我們搞些冰周恩來","box":[[17,451],[566,442],[567,462],[17,471]]},{"text":"高烧時降體温。毛兒蓄没有冰瑰，要到线十里路遠的打鼓山顶上才能搞","box":[[18,483],[567,473],[568,490],[18,500]]},{"text":"到。我們連夜出發，不到十小時就雪山上把冰塊搞回來了，敷在周恩","box":[[17,510],[567,501],[568,521],[17,530]]},{"text":"來的身上退烧。那時的伙食很差，來的穆是藏民的主青稞：一般人","box":[[17,540],[570,529],[571,549],[17,560]]},{"text":"吃了都不消化，别是病人了。我派人搞來了一點小米黍子，这就是","box":[[17,570],[568,559],[569,578],[18,590]]},{"text":"珍貴的東西了，我們給周恩來熬粥喝。：","box":[[20,601],[335,595],[335,612],[20,617]]},{"text":"過草地的弹備工作主要是搞量。毛兒蓋周圆都住了部除，百十里内","box":[[57,629],[569,617],[570,636],[57,648]]},{"text":"搞不到，等的瓣法有三個：一是割老百姓地裹即将成熟成的","box":[[18,658],[569,646],[570,667],[19,679]]},{"text":".","box":[[538,671],[571,671],[571,681],[538,681]]},{"text":"子、青稞二是控野茶草根；三是向下面的部除要一點","box":[[20,688],[484,678],[484,698],[21,708]]},{"text":"割麦子（青稞）要經逼政治機批准：子熟時就在田頭插上牌","box":[[53,718],[571,704],[572,724],[53,738]]},{"text":"子，標明由什座部除收的，明紅軍收子是不得已的現在欠下了","box":[[18,745],[569,732],[570,755],[19,769]]},{"text":"眼，今後一定要還清等等·部除了姿子：中央機關每人都能分到大韵","box":[[20,775],[571,760],[572,783],[21,797]]},{"text":"二十斤，然後用各種方法（多數是用石頭砸）把姿子加工成像片一様的","box":[[20,802],[572,787],[573,814],[21,829]]},{"text":"渣子状的粉這就是過草地的命根子","box":[[18,830],[532,813],[533,843],[19,860]]},{"text":"另外，各部除也向中央機關送来了一些食物，杠一单圆送得最多","box":[[56,861],[565,846],[566,870],[56,885]]},{"text":"毛主席在長征中一直受到红一軍画軍長林能的特别保和照·遇草","box":[[17,890],[567,875],[568,899],[18,914]]},{"text":"地前，林送了一個八個人的架班和一頭贯的子去属毛主席服","box":[[18,915],[569,900],[570,929],[19,944]]},{"text":"務林彪自已的連输員也來了，是我到红一軍圈二師把這支携架除带回","box":[[20,945],[569,929],[570,956],[21,972]]},{"text":"来的，二師師長陳光和政委亞樱再三我要把毛主席照看好·行","box":[[21,971],[568,958],[569,985],[22,998]]},{"text":"方块字读书社区http//booksinozi","box":[[298,1001],[567,1002],[567,1016],[298,1015]]}],"dimensions":{"height":1018,"width":596}}