{"ocr_results":[{"text":"邱會作回憶錄","box":[[615,59],[857,44],[859,80],[617,96]]},{"text":"944","box":[[0,87],[67,87],[67,130],[0,130]]},{"text":"··.··.·","box":[[579,116],[817,104],[819,134],[581,146]]},{"text":"級斡部典型的优良作風，是值得學留的。黄永勝同志的這種好作","box":[[144,266],[1472,229],[1474,305],[146,342]]},{"text":"風，深深地印在我的心中。","box":[[154,371],[647,349],[649,389],[156,411]]},{"text":"在延安同黄永勝同志一面之交之後，四六年六月間我們在熱","box":[[237,423],[1470,393],[1472,463],[239,492]]},{"text":"河承德又见面了。我当時由軍部北平執行部回到承德，黄永勝","box":[[147,508],[1469,477],[1470,539],[148,570]]},{"text":"任熱隧司令員。当时冀熱分局决定把熱隧改為熱軍","box":[[147,586],[1469,557],[1470,619],[148,649]]},{"text":"區，黄永勝任司令。他建我任軍區政治部主任，我們就第一次","box":[[149,665],[1470,637],[1471,699],[150,727]]},{"text":"共事了。此後熱隧改為熱軍區，下十六、十七、十八三","box":[[151,749],[1464,721],[1465,775],[153,803]]},{"text":"個旅和熱中、熱東、熱北，西四個分區。這是備國民軍隧","box":[[150,826],[1468,802],[1469,857],[151,881]]},{"text":"占领承德後的作部署，此後，在解放爭期間，我同黄永勝先","box":[[154,907],[1467,886],[1468,937],[154,958]]},{"text":"後七次共事。我們之間，共事開始，到同時關起來，同時投進","box":[[155,986],[1467,967],[1468,1018],[156,1036]]},{"text":"，同時受密，同時在鬼世界度日都是親密友。現在，黄","box":[[157,1067],[1468,1051],[1469,1099],[158,1114]]},{"text":"永勝同志成了一個冤鬼，我還是一個活著的冤犯。我應該留下一","box":[[159,1146],[1464,1135],[1465,1177],[160,1188]]},{"text":"篇哪怕是很的文字，也要來悼念我親愛的友，以表我的哀","box":[[161,1227],[1466,1216],[1467,1256],[162,1267]]},{"text":"思！","box":[[162,1301],[237,1301],[237,1352],[162,1352]]},{"text":"黄永勝同志是一個有很多优點的领導幹部。選其要者來，","box":[[257,1383],[1432,1380],[1432,1420],[257,1423]]},{"text":"他就是一個有领導能力，軍事指才能很高的高級指員，是一","box":[[169,1459],[1466,1457],[1466,1501],[169,1504]]},{"text":"個軍政雙全的高級领導幹部。在這裹，我對他不能做全面的","box":[[168,1536],[1470,1537],[1470,1584],[168,1583]]},{"text":"述，祗能谈個主要點。","box":[[170,1610],[661,1618],[661,1662],[169,1654]]},{"text":"自參加革命，英勇门。黄永勝同志一九二七年六月就到","box":[[267,1690],[1474,1697],[1474,1748],[267,1741]]},{"text":"武昌中央國民革命政府警衛團當兵。警衛團内有很多共產人。","box":[[174,1765],[1446,1777],[1446,1832],[173,1820]]},{"text":"他去當兵是為了谋生，但當兵始就受到了共產黛的教育，到","box":[[176,1840],[1479,1852],[1478,1911],[175,1898]]},{"text":"警衛團就成了革命士。一九二七年秋武昌國民政府警衛團參加","box":[[177,1916],[1478,1933],[1477,1992],[176,1974]]},{"text":"了秋收起羲上了井罔山，成了中國工紅軍最早的部隧之一。警","box":[[182,1989],[1482,2009],[1481,2074],[181,2054]]},{"text":"衛團出了一批紅軍高級斡部，黄永勝也是「井网山的同志們」之","box":[[182,2064],[1483,2087],[1482,2153],[181,2130]]},{"text":"中的高級领導幹部之一。","box":[[196,2146],[630,2161],[629,2201],[195,2186]]},{"text":"上井罔山的時候，黄永勝還是一個班长。後來在中央蘇區","box":[[280,2219],[1484,2243],[1483,2309],[278,2285]]},{"text":"年的門爭中，他由班長、排长、連长、營长、團長，一步不缺地","box":[[191,2287],[1489,2318],[1487,2391],[189,2360]]},{"text":"當到了師长。黄永滕在江西瑞金，還當过軍委特務營營长保衛中","box":[[194,2362],[1488,2393],[1486,2466],[192,2434]]},{"text":"央，日夜奥毛主席相處，很年輕的時候就得到了毛主席的親自教","box":[[195,2433],[1491,2468],[1489,2544],[193,2509]]},{"text":"導。","box":[[206,2514],[270,2514],[270,2566],[206,2566]]},{"text":"方块字读书社区制作","box":[[1189,2591],[1408,2591],[1408,2621],[1189,2621]]}],"dimensions":{"height":2694,"width":1561}}